azure_simple_pipeline/__init__.py
tests/__init__.py
azure_simple_pipeline-0.0.1.dist-info/LICENSE
azure_simple_pipeline-0.0.1.dist-info/METADATA
azure_simple_pipeline-0.0.1.dist-info/WHEEL
azure_simple_pipeline-0.0.1.dist-info/top_level.txt
azure_simple_pipeline-0.0.1.dist-info/RECORD
